torchmate/__init__.py
torchmate/__version__.py
torchmate/callbacks/__init__.py
torchmate/callbacks/callback.py
torchmate/callbacks/csv_logger.py
torchmate/callbacks/early_stopper.py
torchmate/callbacks/gradient_accumulator.py
torchmate/callbacks/gradient_clipper.py
torchmate/callbacks/model_checkpoint.py
torchmate/callbacks/wandb_logger.py
torchmate/callbacks/wandb_model_checkpoint.py
torchmate/modules/__init__.py
torchmate/modules/refined_self_attention_sagan.py
torchmate/modules/squeeze_and_excitation.py
torchmate/trainer/__init__.py
torchmate/trainer/trainer.py
torchmate/utils/__init__.py
torchmate/utils/check_model_info.py
torchmate/utils/color_text.py
torchmate/utils/history_plotter.py
torchmate/utils/progress_bar.py
torchmate/utils/running_average.py
torchmate-0.1.1.dist-info/LICENSE.txt
torchmate-0.1.1.dist-info/METADATA
torchmate-0.1.1.dist-info/WHEEL
torchmate-0.1.1.dist-info/top_level.txt
torchmate-0.1.1.dist-info/RECORD
