Metadata-Version: 2.1
Name: torchmate
Version: 0.1.1
Summary: Torchmate: A High level PyTorch Training Library
Home-page: UNKNOWN
Author: Abdullah Saihan Taki
Author-email: saihan0176@gmail.com
License: MIT
Project-URL: Homepage, https://github.com/SaihanTaki/torchmate
Project-URL: Documentation, https://torchmate.readthedocs.io/en/latest/
Platform: UNKNOWN
Classifier: Development Status :: 3 - Alpha
Classifier: Intended Audience :: Developers
Classifier: License :: OSI Approved :: MIT License
Classifier: Operating System :: OS Independent
Classifier: Programming Language :: Python :: 3
Classifier: Programming Language :: Python :: 3.9
Classifier: Programming Language :: Python :: 3.10
Classifier: Topic :: Scientific/Engineering :: Artificial Intelligence
Requires-Python: >=3.9.0
License-File: LICENSE.txt
Requires-Dist: numpy >=1.26.4
Requires-Dist: wandb >=0.16.3
Requires-Dist: matplotlib >=3.8.3
Provides-Extra: all
Requires-Dist: pytest >=8.0.1 ; extra == 'all'
Requires-Dist: pytest-mock >=3.12.0 ; extra == 'all'
Requires-Dist: coverage >=7.4.1 ; extra == 'all'
Requires-Dist: pytest-cov >=5.0.0 ; extra == 'all'
Requires-Dist: six >=1.16.0 ; extra == 'all'
Requires-Dist: pre-commit >=3.6.2 ; extra == 'all'
Requires-Dist: black >=24.1.1 ; extra == 'all'
Requires-Dist: flake8 >=7.0.0 ; extra == 'all'
Requires-Dist: isort >=5.13.2 ; extra == 'all'
Requires-Dist: Sphinx ==7.2.6 ; extra == 'all'
Requires-Dist: sphinx-copybutton ==0.5.2 ; extra == 'all'
Requires-Dist: sphinx-notfound-page ==1.0.0 ; extra == 'all'
Requires-Dist: sphinx-rtd-theme ==2.0.0 ; extra == 'all'
Requires-Dist: sphinxcontrib-applehelp ==1.0.8 ; extra == 'all'
Requires-Dist: sphinxcontrib-devhelp ==1.0.6 ; extra == 'all'
Requires-Dist: sphinxcontrib-htmlhelp ==2.0.5 ; extra == 'all'
Requires-Dist: sphinxcontrib-jquery ==4.1 ; extra == 'all'
Requires-Dist: sphinxcontrib-jsmath ==1.0.1 ; extra == 'all'
Requires-Dist: sphinxcontrib-qthelp ==1.0.7 ; extra == 'all'
Requires-Dist: sphinxcontrib-serializinghtml ==1.1.10 ; extra == 'all'
Requires-Dist: autodocsumm ==0.2.12 ; extra == 'all'
Requires-Dist: nbsphinx ==0.9.3 ; extra == 'all'
Provides-Extra: dev
Requires-Dist: pytest >=8.0.1 ; extra == 'dev'
Requires-Dist: pytest-mock >=3.12.0 ; extra == 'dev'
Requires-Dist: coverage >=7.4.1 ; extra == 'dev'
Requires-Dist: pytest-cov >=5.0.0 ; extra == 'dev'
Requires-Dist: six >=1.16.0 ; extra == 'dev'
Requires-Dist: pre-commit >=3.6.2 ; extra == 'dev'
Requires-Dist: black >=24.1.1 ; extra == 'dev'
Requires-Dist: flake8 >=7.0.0 ; extra == 'dev'
Requires-Dist: isort >=5.13.2 ; extra == 'dev'
Provides-Extra: docs
Requires-Dist: Sphinx ==7.2.6 ; extra == 'docs'
Requires-Dist: sphinx-copybutton ==0.5.2 ; extra == 'docs'
Requires-Dist: sphinx-notfound-page ==1.0.0 ; extra == 'docs'
Requires-Dist: sphinx-rtd-theme ==2.0.0 ; extra == 'docs'
Requires-Dist: sphinxcontrib-applehelp ==1.0.8 ; extra == 'docs'
Requires-Dist: sphinxcontrib-devhelp ==1.0.6 ; extra == 'docs'
Requires-Dist: sphinxcontrib-htmlhelp ==2.0.5 ; extra == 'docs'
Requires-Dist: sphinxcontrib-jquery ==4.1 ; extra == 'docs'
Requires-Dist: sphinxcontrib-jsmath ==1.0.1 ; extra == 'docs'
Requires-Dist: sphinxcontrib-qthelp ==1.0.7 ; extra == 'docs'
Requires-Dist: sphinxcontrib-serializinghtml ==1.1.10 ; extra == 'docs'
Requires-Dist: autodocsumm ==0.2.12 ; extra == 'docs'
Requires-Dist: nbsphinx ==0.9.3 ; extra == 'docs'
Provides-Extra: style
Requires-Dist: pre-commit >=3.6.2 ; extra == 'style'
Requires-Dist: black >=24.1.1 ; extra == 'style'
Requires-Dist: flake8 >=7.0.0 ; extra == 'style'
Requires-Dist: isort >=5.13.2 ; extra == 'style'
Provides-Extra: tests
Requires-Dist: pytest >=8.0.1 ; extra == 'tests'
Requires-Dist: pytest-mock >=3.12.0 ; extra == 'tests'
Requires-Dist: coverage >=7.4.1 ; extra == 'tests'
Requires-Dist: pytest-cov >=5.0.0 ; extra == 'tests'
Requires-Dist: six >=1.16.0 ; extra == 'tests'
